cli.py
swarmcli/__init__.py
swarmcli/builders.py
swarmcli/clients.py
swarmcli/facade.py
swarmcli/from_db.py
swarmcli/utils.py
swarmcli/cli_commands/__init__.py
swarmcli/cli_commands/cli_agent.py
swarmcli/cli_commands/cli_framework.py
swarmcli/cli_commands/cli_swarm.py
swarmcli/cli_commands/cli_tool.py
swarmcli/cli_commands/cli_user.py
swarmbase_cli-0.1.4.dist-info/METADATA
swarmbase_cli-0.1.4.dist-info/WHEEL
swarmbase_cli-0.1.4.dist-info/entry_points.txt
swarmbase_cli-0.1.4.dist-info/top_level.txt
swarmbase_cli-0.1.4.dist-info/RECORD
