Metadata-Version: 2.1
Name: swarmbase-cli
Version: 0.1.4
Summary: A CLI for interacting with the swarmbase.ai API
Home-page: https://github.com/Go-Pomegranate/swarmbase-cli
Author: swarmbase.ai
Author-email: eryk.panter@swarmbase.ai
Requires-Dist: click
Requires-Dist: requests
Requires-Dist: pydantic
